{
  "date": "2026-02-18",
  "projects": {
    "Bot V1.2": {
      "totalLinesAdded": 801,
      "totalLinesRemoved": 16,
      "totalActiveTime": 9,
      "files": {
        "c:\\Users\\Van\\OneDrive\\Desktop\\Bot V1.2\\bot\\public\\dashboard.css": [
          {
            "timestamp": "2026-02-18T12:34:34.928Z",
            "fileName": "c:\\Users\\Van\\OneDrive\\Desktop\\Bot V1.2\\bot\\public\\dashboard.css",
            "fileType": ".css",
            "linesAdded": 773,
            "linesRemoved": 0,
            "projectName": "Bot V1.2",
            "content": {
              "added": [],
              "removed": []
            },
            "duration": 0,
            "language": "css"
          },
          {
            "timestamp": "2026-02-18T12:36:41.221Z",
            "fileName": "c:\\Users\\Van\\OneDrive\\Desktop\\Bot V1.2\\bot\\public\\dashboard.css",
            "fileType": ".css",
            "linesAdded": 0,
            "linesRemoved": 16,
            "projectName": "Bot V1.2",
            "content": {
              "added": [],
              "removed": []
            },
            "duration": 3,
            "language": "css"
          }
        ],
        "c:\\Users\\Van\\AppData\\Roaming\\Windsurf\\User\\settings.json": [
          {
            "timestamp": "2026-02-18T12:41:05.644Z",
            "fileName": "c:\\Users\\Van\\AppData\\Roaming\\Windsurf\\User\\settings.json",
            "fileType": ".json",
            "linesAdded": 27,
            "linesRemoved": 0,
            "projectName": "Bot V1.2",
            "content": {
              "added": [],
              "removed": []
            },
            "duration": 5,
            "language": "json"
          },
          {
            "timestamp": "2026-02-18T12:41:05.753Z",
            "fileName": "c:\\Users\\Van\\AppData\\Roaming\\Windsurf\\User\\settings.json",
            "fileType": ".json",
            "linesAdded": 1,
            "linesRemoved": 0,
            "projectName": "Bot V1.2",
            "content": {
              "added": [],
              "removed": []
            },
            "duration": 1,
            "language": "json"
          }
        ]
      },
      "languageStats": {
        "css": 3
      },
      "changeFrequency": {
        "9": 3
      },
      "topFiles": [
        "c:\\Users\\Van\\OneDrive\\Desktop\\Bot V1.2\\bot\\public\\dashboard.css"
      ],
      "averageChangeSize": 394.5
    }
  },
  "totalActiveTime": 3,
  "totalProjects": 1,
  "totalFiles": 1,
  "mostActiveHours": [
    9
  ],
  "mostUsedLanguages": [
    "css"
  ]
}